djaodjin_extended_templates-0.4.12.dist-info/licenses/LICENSE.txt
extended_templates/__init__.py
extended_templates/compat.py
extended_templates/decorators.py
extended_templates/docs.py
extended_templates/extras.py
extended_templates/helpers.py
extended_templates/mixins.py
extended_templates/models.py
extended_templates/settings.py
extended_templates/signals.py
extended_templates/themes.py
extended_templates/thread_locals.py
extended_templates/uploadhandler.py
extended_templates/utils.py
extended_templates/api/__init__.py
extended_templates/api/less_variables.py
extended_templates/api/serializers.py
extended_templates/api/sitecss.py
extended_templates/api/sources.py
extended_templates/api/themes.py
extended_templates/api/upload_media.py
extended_templates/backends/__init__.py
extended_templates/backends/base.py
extended_templates/backends/eml.py
extended_templates/backends/pdf.py
extended_templates/backends/s3.py
extended_templates/management/__init__.py
extended_templates/management/commands/__init__.py
extended_templates/management/commands/install_theme.py
extended_templates/management/commands/list_css_classes.py
extended_templates/static/js/djaodjin-code-editor.js
extended_templates/static/js/djaodjin-editor.js
extended_templates/static/js/djaodjin-panel-buttons.js
extended_templates/static/js/djaodjin-resources-vue.js
extended_templates/static/js/djaodjin-resources.js
extended_templates/static/js/djaodjin-sidebar-gallery.js
extended_templates/static/js/djaodjin-style-editor.js
extended_templates/static/js/djaodjin-themes-vue.js
extended_templates/static/js/djaodjin-upload.js
extended_templates/templates/extended_templates/_body_bottom_edit_tools.html
extended_templates/templates/extended_templates/edit.html
extended_templates/templates/extended_templates/theme.html
extended_templates/templatetags/__init__.py
extended_templates/templatetags/extended_templates_tags.py
extended_templates/urls/__init__.py
extended_templates/urls/api/__init__.py
extended_templates/urls/api/assets.py
extended_templates/urls/api/edittools.py
djaodjin_extended_templates-0.4.12.dist-info/METADATA
djaodjin_extended_templates-0.4.12.dist-info/WHEEL
djaodjin_extended_templates-0.4.12.dist-info/top_level.txt
djaodjin_extended_templates-0.4.12.dist-info/RECORD
