Metadata-Version: 2.4
Name: djaodjin-extended-templates
Version: 0.4.12
Summary: DjaoDjin's Template wrappers for HTML email and PDF templates
Author-email: The DjaoDjin Team <help@djaodjin.com>
Maintainer-email: The DjaoDjin Team <help@djaodjin.com>
License: BSD-2-Clause
Project-URL: repository, https://github.com/djaodjin/djaodjin-extended-templates
Project-URL: documentation, https://djaodjin-extended-templates.readthedocs.io/
Project-URL: changelog, https://github.com/djaodjin/djaodjin-extended-templates/changelog
Keywords: django,templates,email,pdf
Classifier: Framework :: Django
Classifier: Environment :: Web Environment
Classifier: Programming Language :: Python
Classifier: License :: OSI Approved :: BSD License
Requires-Python: >=3.7
License-File: LICENSE.txt
Requires-Dist: beautifulsoup4>=4.3.2
Requires-Dist: Django>=1.11
Requires-Dist: djangorestframework>=3.3.1
Requires-Dist: django-storages>=1.14
Requires-Dist: djaodjin-deployutils>=0.14.1
Requires-Dist: Jinja2>=2.8
Requires-Dist: premailer>=2.9.2
Requires-Dist: requests>=2.22.0
Requires-Dist: WeasyPrint>=0.42
Dynamic: license-file
